README
setup.py
wsgistate/__init__.py
wsgistate/cache.py
wsgistate/db.py
wsgistate/file.py
wsgistate/memcached.py
wsgistate/memory.py
wsgistate/session.py
wsgistate/simple.py
wsgistate.egg-info/PKG-INFO
wsgistate.egg-info/SOURCES.txt
wsgistate.egg-info/dependency_links.txt
wsgistate.egg-info/entry_points.txt
wsgistate.egg-info/not-zip-safe
wsgistate.egg-info/requires.txt
wsgistate.egg-info/top_level.txt
wsgistate/tests/__init__.py
wsgistate/tests/test_wsgistate.py
