Metadata-Version: 1.0
Name: wsgistate
Version: 0.4.2
Summary: WSGI session and caching middleware.
Home-page: http://pypi.python.org/pypi/wsgistate/
Author: L. C. Rees
Author-email: lcrees@gmail.com
License: BSD
Keywords: WSGI session caching persistence memoizing HTTP Web
Platform: UNKNOWN
Classifier: Development Status :: 4 - Beta
Classifier: Environment :: Web Environment
Classifier: License :: OSI Approved :: BSD License
Classifier: Natural Language :: English
Classifier: Operating System :: OS Independent
Classifier: Programming Language :: Python
Classifier: Topic :: Internet :: WWW/HTTP :: WSGI :: Middleware
